{
  "version": "1.0",
  "items": {
    "Basic Plots": [
      {
        "id": "BasicLine",
        "name": "Basic line series",
        "text": "An easy way to get started with line series."
      },
      {
        "id": "BasicBar",
        "name": "Basic bar series",
        "text": "Get started with the bar series class."
      },
      {
        "id": "BasicStackedBar",
        "name": "Basic stacked bar series",
        "text": "A bar series that stacks the content."
      },
      {
        "id": "BasicScatter",
        "name": "Basic scatter series",
        "text": "Only a points series that explicitly sets X and Y coordinates."
      },
      {
        "id": "BasicBubble",
        "name": "Basic bubble series",
        "text": "Similar to a scatter series, but the points are weithed."
      },
      {
        "id": "BasicHeat",
        "name": "Heat series",
        "text": "Heat series based on the weight of every point."
      },
      {
        "id": "InvertedSeries",
        "name": "Inverted series",
        "text": "Invert series using InvertAxes property."
      },
      {
        "id": "AxisSections",
        "name": "Axis sections",
        "text": "A chart that highlights a range in an axis."
      },
      {
        "id": "MultipleAxes",
        "name": "Multiple axes",
        "text": "A chart that scales its series in multiple axes."
      },
      {
        "id": "DataLabels",
        "name": "Data Labels",
        "text": "Set DataLabels = true in any series to display a label in every point."
      },
      {
        "id": "BasicPie",
        "name": "Basic Pie chart",
        "text": "Generate pie charts easily"
      }
    ],
    "Features": [
      
    ]
  }
}